{
    "id": 8056910,
    "joined_time": "2024-08-16T13:58:40.007302Z",
    "started_event": 1,
    "favourite_team": 13,
    "player_first_name": "Gustav",
    "player_last_name": "Gyldenvang",
    "player_region_id": 58,
    "player_region_name": "Denmark",
    "player_region_iso_code_short": "DK",
    "player_region_iso_code_long": "DNK",
    "years_active": 4,
    "summary_overall_points": 387,
    "summary_overall_rank": 5164303,
    "summary_event_points": 37,
    "summary_event_rank": 8000342,
    "current_event": 7,
    "leagues": {
        "classic": [
            {
                "id": 13,
                "name": "Man City",
                "short_name": "team-13",
                "created": "2024-07-17T11:51:46.339404Z",
                "closed": false,
                "rank": null,
                "max_entries": null,
                "league_type": "s",
                "scoring": "c",
                "admin_entry": null,
                "start_event": 1,
                "entry_can_leave": false,
                "entry_can_admin": false,
                "entry_can_invite": false,
                "has_cup": true,
                "cup_league": null,
                "cup_qualified": null,
                "rank_count": 1192266,
                "entry_percentile_rank": 45,
                "active_phases": [
                    {
                        "phase": 1,
                        "rank": 510164,
                        "last_rank": 454475,
                        "rank_sort": 510182,
                        "total": 387,
                        "league_id": 13,
                        "rank_count": 1192266,
                        "entry_percentile_rank": 45
                    },
                    {
                        "phase": 4,
                        "rank": 872798,
                        "last_rank": 0,
                        "rank_sort": 873353,
                        "total": 37,
                        "league_id": 13,
                        "rank_count": 1192265,
                        "entry_percentile_rank": 75
                    }
                ],
                "entry_rank": 510164,
                "entry_last_rank": 454475
            },
            {
                "id": 78,
                "name": "Denmark",
                "short_name": "region-58",
                "created": "2024-07-17T11:51:46.843524Z",
                "closed": false,
                "rank": null,
                "max_entries": null,
                "league_type": "s",
                "scoring": "c",
                "admin_entry": null,
                "start_event": 1,
                "entry_can_leave": false,
                "entry_can_admin": false,
                "entry_can_invite": false,
                "has_cup": true,
                "cup_league": null,
                "cup_qualified": null,
                "rank_count": 60219,
                "entry_percentile_rank": 50,
                "active_phases": [
                    {
                        "phase": 1,
                        "rank": 28913,
                        "last_rank": 25476,
                        "rank_sort": 28914,
                        "total": 387,
                        "league_id": 78,
                        "rank_count": 60219,
                        "entry_percentile_rank": 50
                    },
                    {
                        "phase": 4,
                        "rank": 44055,
                        "last_rank": 0,
                        "rank_sort": 44087,
                        "total": 37,
                        "league_id": 78,
                        "rank_count": 60219,
                        "entry_percentile_rank": 75
                    }
                ],
                "entry_rank": 28913,
                "entry_last_rank": 25476
            },
            {
                "id": 276,
                "name": "Gameweek 1",
                "short_name": "event-1",
                "created": "2024-07-17T11:51:48.316462Z",
                "closed": false,
                "rank": null,
                "max_entries": null,
                "league_type": "s",
                "scoring": "c",
                "admin_entry": null,
                "start_event": 1,
                "entry_can_leave": false,
                "entry_can_admin": false,
                "entry_can_invite": false,
                "has_cup": false,
                "cup_league": null,
                "cup_qualified": null,
                "rank_count": 8587976,
                "entry_percentile_rank": 60,
                "active_phases": [
                    {
                        "phase": 1,
                        "rank": 5118297,
                        "last_rank": 4502188,
                        "rank_sort": 5118404,
                        "total": 387,
                        "league_id": 276,
                        "rank_count": 8587976,
                        "entry_percentile_rank": 60
                    },
                    {
                        "phase": 4,
                        "rank": 6646766,
                        "last_rank": 0,
                        "rank_sort": 6650074,
                        "total": 37,
                        "league_id": 276,
                        "rank_count": 8587971,
                        "entry_percentile_rank": 80
                    }
                ],
                "entry_rank": 5118297,
                "entry_last_rank": 4502188
            },
            {
                "id": 314,
                "name": "Overall",
                "short_name": "overall",
                "created": "2024-07-17T11:51:48.594925Z",
                "closed": false,
                "rank": null,
                "max_entries": null,
                "league_type": "s",
                "scoring": "c",
                "admin_entry": null,
                "start_event": 1,
                "entry_can_leave": false,
                "entry_can_admin": false,
                "entry_can_invite": false,
                "has_cup": true,
                "cup_league": null,
                "cup_qualified": null,
                "rank_count": 10466712,
                "entry_percentile_rank": 50,
                "active_phases": [
                    {
                        "phase": 1,
                        "rank": 5164303,
                        "last_rank": 4526137,
                        "rank_sort": 5164418,
                        "total": 387,
                        "league_id": 314,
                        "rank_count": 10466712,
                        "entry_percentile_rank": 50
                    },
                    {
                        "phase": 4,
                        "rank": 8000337,
                        "last_rank": 0,
                        "rank_sort": 8004322,
                        "total": 37,
                        "league_id": 314,
                        "rank_count": 10466702,
                        "entry_percentile_rank": 80
                    }
                ],
                "entry_rank": 5164303,
                "entry_last_rank": 4526137
            },
            {
                "id": 321,
                "name": "Second Chance",
                "short_name": "sc",
                "created": "2024-07-17T11:51:48.646333Z",
                "closed": false,
                "rank": null,
                "max_entries": null,
                "league_type": "s",
                "scoring": "c",
                "admin_entry": null,
                "start_event": 20,
                "entry_can_leave": false,
                "entry_can_admin": false,
                "entry_can_invite": false,
                "has_cup": false,
                "cup_league": null,
                "cup_qualified": null,
                "rank_count": null,
                "entry_percentile_rank": null,
                "active_phases": [
                    {
                        "phase": 1,
                        "rank": 0,
                        "last_rank": 0,
                        "rank_sort": 0,
                        "total": 0,
                        "league_id": 321,
                        "rank_count": null,
                        "entry_percentile_rank": null
                    },
                    {
                        "phase": 4,
                        "rank": 0,
                        "last_rank": 0,
                        "rank_sort": 0,
                        "total": 0,
                        "league_id": 321,
                        "rank_count": null,
                        "entry_percentile_rank": null
                    }
                ],
                "entry_rank": 0,
                "entry_last_rank": 0
            },
            {
                "id": 782337,
                "name": "VS BOIS Fantasy",
                "short_name": null,
                "created": "2024-08-07T20:03:02.384180Z",
                "closed": false,
                "rank": null,
                "max_entries": null,
                "league_type": "x",
                "scoring": "c",
                "admin_entry": 3682099,
                "start_event": 1,
                "entry_can_leave": true,
                "entry_can_admin": false,
                "entry_can_invite": false,
                "has_cup": true,
                "cup_league": null,
                "cup_qualified": null,
                "rank_count": 9,
                "entry_percentile_rank": 70,
                "active_phases": [
                    {
                        "phase": 1,
                        "rank": 6,
                        "last_rank": 6,
                        "rank_sort": 6,
                        "total": 387,
                        "league_id": 782337,
                        "rank_count": 9,
                        "entry_percentile_rank": 70
                    },
                    {
                        "phase": 4,
                        "rank": 7,
                        "last_rank": 0,
                        "rank_sort": 7,
                        "total": 37,
                        "league_id": 782337,
                        "rank_count": 9,
                        "entry_percentile_rank": 80
                    }
                ],
                "entry_rank": 6,
                "entry_last_rank": 6
            },
            {
                "id": 1193702,
                "name": "Viaplay League",
                "short_name": "brd-viaplay",
                "created": "2024-08-13T14:38:51.766579Z",
                "closed": false,
                "rank": null,
                "max_entries": null,
                "league_type": "s",
                "scoring": "c",
                "admin_entry": null,
                "start_event": 1,
                "entry_can_leave": false,
                "entry_can_admin": false,
                "entry_can_invite": false,
                "has_cup": false,
                "cup_league": null,
                "cup_qualified": null,
                "rank_count": 620013,
                "entry_percentile_rank": 55,
                "active_phases": [
                    {
                        "phase": 1,
                        "rank": 334032,
                        "last_rank": 296458,
                        "rank_sort": 334043,
                        "total": 387,
                        "league_id": 1193702,
                        "rank_count": 620013,
                        "entry_percentile_rank": 55
                    },
                    {
                        "phase": 4,
                        "rank": 467426,
                        "last_rank": 0,
                        "rank_sort": 467714,
                        "total": 37,
                        "league_id": 1193702,
                        "rank_count": 620012,
                        "entry_percentile_rank": 80
                    }
                ],
                "entry_rank": 334032,
                "entry_last_rank": 296458
            }
        ],
        "h2h": [],
        "cup": {
            "matches": [],
            "status": {
                "qualification_event": null,
                "qualification_numbers": null,
                "qualification_rank": null,
                "qualification_state": null
            },
            "cup_league": null
        },
        "cup_matches": []
    },
    "name": "Goldenfield CF",
    "name_change_blocked": false,
    "entered_events": [
        1,
        2,
        3,
        4,
        5,
        6,
        7
    ],
    "kit": null,
    "last_deadline_bank": 0,
    "last_deadline_value": 995,
    "last_deadline_total_transfers": 0
}